{"title": "89164", "id": "nonns_89164", "links": [{"href": "https:/archaeolink.github.io/AncientPorts_RDF/collections/nonns_89164/items/index.json", "rel": "items", "type": "application/json", "title": "Collection as JSON"}, {"href": "https:/archaeolink.github.io/AncientPorts_RDF/collections/nonns_89164/items/indexc.html", "rel": "items", "type": "text/html", "title": "Collection as HTML"}, {"href": "https:/archaeolink.github.io/AncientPorts_RDF/collections/nonns_89164/items/index.ttl", "rel": "collection", "type": "text/ttl", "title": "Collection as TTL"}]}