{"http://purl.org/dc/elements/1.1/created": ["2023"], "http://purl.org/dc/elements/1.1/creator": ["http://data.archaeology.link/data/spphaefen/arthur_de_graauw"], "http://www.opengis.net/ont/geosparql#hasGeometry": ["http://data.archaeology.link/data/ancientports/975_geom"], "http://www.w3.org/1999/02/22-rdf-syntax-ns#type": ["http://www.ancientports.com/ont#Harbour"], "http://www.w3.org/2000/01/rdf-schema#label": ["Cuma, with uncertain location of ancient port NE and/or SW of the acropolis, and uncertain Fossa Neronis"], "http://www.w3.org/2002/07/owl#sameAs": ["http://www.wikidata.org/entity/Q243456"], "http://www.w3.org/2004/02/skos/core#note": ["Poupet (2005)", "Vecchi (2000)"], "http://www.w3.org/2006/time#hasTime": ["http://data.archaeology.link/data/ancientports/975_foundation"], "http://www.wikidata.org/prop/direct/P1584": ["http://pleiades.stoa.org/places/432808"], "http://www.wikidata.org/prop/direct/P17": ["http://www.wikidata.org/entity/Q38"], "http://www.wikidata.org/prop/direct/P1936": ["http://imperium.ahlfeldt.se/places/16719"], "http://www.wikidata.org/prop/direct/P1958": ["https://www.trismegistos.org/place/14437"], "http://www.wikidata.org/prop/direct/P8068": ["https://topostext.org/place/408141PCum"]}