{"title": "31074", "id": "nonns_31074", "links": [{"href": "https:/archaeolink.github.io/AncientPorts_RDF/collections/nonns_31074/items/index.json", "rel": "items", "type": "application/json", "title": "Collection as JSON"}, {"href": "https:/archaeolink.github.io/AncientPorts_RDF/collections/nonns_31074/items/indexc.html", "rel": "items", "type": "text/html", "title": "Collection as HTML"}, {"href": "https:/archaeolink.github.io/AncientPorts_RDF/collections/nonns_31074/items/index.ttl", "rel": "collection", "type": "text/ttl", "title": "Collection as TTL"}], "itemType": "feature", "extent": {"spatial": {"bbox": [22.737, 37.5808, 22.737, 37.5808], "crs": "http://www.opengis.net/def/crs/EPSG/0/4326"}}, "crs": "http://www.opengis.net/def/crs/EPSG/0/4326"}