{"http://purl.org/dc/elements/1.1/created": ["2012"], "http://purl.org/dc/elements/1.1/creator": ["http://data.archaeology.link/data/ancientports/author_Carreras_Cesar", "http://data.archaeology.link/data/ancientports/author_Morais_Rui"], "http://purl.org/dc/elements/1.1/title": ["The Atlantic Roman trade during the Principate: new evidence from the western facade"], "http://purl.org/dc/terms/publisher": ["http://www.wikidata.org/entity/Q70631906"], "http://purl.org/ontology/bibo/issuer": ["Oxford Journal of Archaeology"], "http://purl.org/ontology/bibo/number": ["4"], "http://purl.org/ontology/bibo/pageEnd": ["441"], "http://purl.org/ontology/bibo/pageStart": ["419"], "http://purl.org/ontology/bibo/volume": ["31"], "http://rdfs.org/ns/void#inDataset": ["http://data.archaeology.link/data/ancientports/dataset"], "http://www.w3.org/1999/02/22-rdf-syntax-ns#type": ["http://purl.org/ontology/bibo/Article"]}