{"http://purl.org/dc/elements/1.1/created": ["2003"], "http://purl.org/dc/elements/1.1/creator": ["http://data.archaeology.link/data/ancientports/author_Steerwood_Robert"], "http://purl.org/dc/elements/1.1/title": ["A Context for Sitomagus: Romano-British Settlement in the Suffolk Mid-Coastal Area"], "http://purl.org/ontology/bibo/number": ["3"], "http://purl.org/ontology/bibo/pageEnd": ["261"], "http://purl.org/ontology/bibo/pageStart": ["253"], "http://purl.org/ontology/bibo/volume": ["40"], "http://rdfs.org/ns/void#inDataset": ["http://data.archaeology.link/data/ancientports/dataset"], "http://www.w3.org/1999/02/22-rdf-syntax-ns#type": ["http://purl.org/ontology/bibo/Proceedings"]}