{"http://rdfs.org/ns/void#linkPredicate": ["http://www.wikidata.org/prop/direct/P1936", "http://www.wikidata.org/prop/direct/P1584"], "http://rdfs.org/ns/void#objectsTarget": ["http://pleiades.stoa.org/places/", "https://pleiades.stoa.org/places/"], "http://rdfs.org/ns/void#subjectsTarget": ["http://data.archaeology.link/data/ancientports/ap_dataset"], "http://rdfs.org/ns/void#triples": ["238", "1", "3390"], "http://www.w3.org/1999/02/22-rdf-syntax-ns#type": ["http://rdfs.org/ns/void#Linkset"], "http://www.w3.org/2000/01/rdf-schema#label": ["Linkset: ap_dataset - places", "Linkset: ap_dataset - Pleiades Places (ple:)"]}